florestmessangerapi/__init__.py
florestmessangerapi-1.8.dist-info/METADATA
florestmessangerapi-1.8.dist-info/WHEEL
florestmessangerapi-1.8.dist-info/top_level.txt
florestmessangerapi-1.8.dist-info/RECORD
