Metadata-Version: 2.4
Name: florestmessangerapi
Version: 1.8
Summary: API для FlorestMessanger (BOT).
Author: florestdev
Author-email: florestone4185@internet.ru
Project-URL: Social Resources, https://taplink.cc/florestone4185
Project-URL: Messanger, https://florestmsgs-florestdev4185.amvera.io/chat
Project-URL: API Docs, https://florestmsgs-florestdev4185.amvera.io/api_docs
Requires-Python: >=3.10
Requires-Dist: requests
Requires-Dist: colorama
Requires-Dist: aiohttp
Dynamic: author
Dynamic: author-email
Dynamic: description
Dynamic: project-url
Dynamic: requires-dist
Dynamic: requires-python
Dynamic: summary
